k53certbot/__init__.py
k53certbot/api.py
k53certbot/cli.py
k53certbot/version.py
k53certbot-0.1.0.dist-info/LICENSE
k53certbot-0.1.0.dist-info/METADATA
k53certbot-0.1.0.dist-info/WHEEL
k53certbot-0.1.0.dist-info/entry_points.txt
k53certbot-0.1.0.dist-info/top_level.txt
k53certbot-0.1.0.dist-info/RECORD
