Metadata-Version: 2.1
Name: k53certbot
Version: 0.1.0
Summary: Kubernetes + Route53 + ACME
Home-page: https://github.com/declarativesystems/k53certbot.git
Author: Geoff Williams
Author-email: geoff@declarativesystems.com
License: UNKNOWN
Platform: UNKNOWN
Classifier: Development Status :: 2 - Pre-Alpha
Classifier: Programming Language :: Python :: 3
Classifier: License :: OSI Approved :: Apache Software License
Classifier: Operating System :: OS Independent
Requires-Python: >=3.6
Requires-Dist: certbot-dns-route53
Requires-Dist: kubernetes
Requires-Dist: loguru
Requires-Dist: docopt
Requires-Dist: requests
